setup.py
mymath/__init__.py
mymath/add.py
mymath/divide.py
mymath/multiply.py
mymath/setup.py
mymath/subtract.py
mymath/adv/__init__.py
mymath/adv/sqrt.py
mymath_newversion_arun.egg-info/PKG-INFO
mymath_newversion_arun.egg-info/SOURCES.txt
mymath_newversion_arun.egg-info/dependency_links.txt
mymath_newversion_arun.egg-info/top_level.txt