Metadata-Version: 1.0
Name: mymath-newversion-arun
Version: 0.1
Summary: A silly math package
Home-page: http://www.mymath.org/
Author: Arunansu Gorai
Author-email: chi.square.revisted@gmail.com
License: UNKNOWN
Platform: UNKNOWN
